lxdui/__init__.py
lxdui/app.py
lxdui/app_metadata/__init__.py
lxdui/app_metadata/__init__.pyc
lxdui/conf/config.json
lxdui/conf/data.json
lxdui/conf/lxd-bridge
lxdui/helpers/BridgeNetwork.py
lxdui/helpers/__init__.py
lxdui/helpers/login_manage.py
lxdui/helpers/response.py
lxdui/static/apple-touch-icon.png
lxdui/static/favicon-16x16.png
lxdui/static/favicon-32x32.png
lxdui/static/favicon.ico
lxdui/static/css/app.css
lxdui/static/css/app.css.1
lxdui/static/css/bootstrap.min.css
lxdui/static/css/toastr.css
lxdui/static/fonts/glyphicons-halflings-regular.eot
lxdui/static/fonts/glyphicons-halflings-regular.svg
lxdui/static/fonts/glyphicons-halflings-regular.ttf
lxdui/static/fonts/glyphicons-halflings-regular.woff
lxdui/static/fonts/glyphicons-halflings-regular.woff2
lxdui/static/images/loader.gif
lxdui/static/images/logo.png
lxdui/static/js/app.js
lxdui/static/js/bootstrap.js
lxdui/static/js/container-details.js
lxdui/static/js/container-details.js.0
lxdui/static/js/container.js
lxdui/static/js/createcontainer.js
lxdui/static/js/html.js
lxdui/static/js/images.js
lxdui/static/js/jquery-2.0.0.js
lxdui/static/js/login.js
lxdui/static/js/toastr.min.js
lxdui/static/templates/components.html
lxdui/templates/container-details.html
lxdui/templates/containers.html
lxdui/templates/images.html
lxdui/templates/images_NO_LXC.html
lxdui/templates/index.html
lxdui/templates/login.html
lxdui/templates/network.html
lxdui/templates/network_nolxdbr0.html
lxdui-1.0.1.dist-info/DESCRIPTION.rst
lxdui-1.0.1.dist-info/METADATA
lxdui-1.0.1.dist-info/RECORD
lxdui-1.0.1.dist-info/WHEEL
lxdui-1.0.1.dist-info/entry_points.txt
lxdui-1.0.1.dist-info/metadata.json
lxdui-1.0.1.dist-info/top_level.txt
